[
    {
        "stock_code": "NVDA.US",
        "expiry_dates": [
            "2026-05-06",
            "2026-05-08",
            "2026-05-11",
            "2026-05-13",
            "2026-05-15",
            "2026-05-18",
            "2026-05-22",
            "2026-05-29",
            "2026-06-05",
            "2026-06-12",
            "2026-06-18"
        ],
        "strike_price_range": [
            100,
            200
        ]
    },
    {
        "stock_code": "PLTR.US",
        "expiry_dates": [
            "2026-05-08",
            "2026-05-15",
            "2026-05-22",
            "2026-05-29",
            "2026-06-05",
            "2026-06-12",
            "2026-06-18"
        ],
        "strike_price_range": [
            80,
            200
        ]
    },
    {
        "stock_code": "TEM.US",
        "expiry_dates": [
            "2026-05-08",
            "2026-05-15",
            "2026-05-22",
            "2026-05-29",
            "2026-06-05",
            "2026-06-12",
            "2026-06-18"
        ],
        "strike_price_range": [
            20,
            80
        ]
    },
    {
        "stock_code": "HOOD.US",
        "expiry_dates": [
            "2026-05-08",
            "2026-05-15",
            "2026-05-22",
            "2026-05-29",
            "2026-06-05",
            "2026-06-12",
            "2026-06-18"
        ],
        "strike_price_range": [
            40,
            90
        ]
    },
    {
        "stock_code": "COIN.US",
        "expiry_dates": [
            "2026-05-08",
            "2026-05-15",
            "2026-05-22",
            "2026-05-29",
            "2026-06-05",
            "2026-06-12",
            "2026-06-18"
        ],
        "strike_price_range": [
            120,
            220
        ]
    },
    {
        "stock_code": "SPY.US",
        "expiry_dates": [
            "2026-05-05",
            "2026-05-06",
            "2026-05-07",
            "2026-05-08",
            "2026-05-11",
            "2026-05-12",
            "2026-05-13",
            "2026-05-14",
            "2026-05-15",
            "2026-05-18",
            "2026-05-22",
            "2026-05-29",
            "2026-06-05",
            "2026-06-12",
            "2026-06-18"
        ],
        "strike_price_range": [
            500,
            750
        ]
    }
]